toobit_api/__init__.py
toobit_api/toobit_api.py
toobit_api_python-0.1.0.dist-info/LICENSE.md
toobit_api_python-0.1.0.dist-info/METADATA
toobit_api_python-0.1.0.dist-info/WHEEL
toobit_api_python-0.1.0.dist-info/top_level.txt
toobit_api_python-0.1.0.dist-info/RECORD
