Metadata-Version: 2.1
Name: toobit-api-python
Version: 0.1.0
Summary: Python client for the TooBit Exchange Trading API
Home-page: https://github.com/AhmetKaracali/toobit-api-python
Author: Ahmet KARAÇALI
Author-email: akaracali58@gmail.com
License-File: LICENSE.md
Requires-Dist: requests
